agent_skill_sdk/__init__.py
agent_skill_sdk/decorators.py
agent_skill_sdk/agent/__init__.py
agent_skill_sdk/agent/context.py
agent_skill_sdk/agent/core.py
agent_skill_sdk/agent/registry.py
agent_skill_sdk/agent/runner.py
agent_skill_sdk/cli/main.py
agent_skill_sdk/config/settings.py
agent_skill_sdk/greengrass/adapter.py
agent_skill_sdk/logs/memory.py
agent_skill_sdk/plugins/__init__.py
agent_skill_sdk/plugins/aws_iot_core.py
agent_skill_sdk/plugins/coap.py
agent_skill_sdk/plugins/cron.py
agent_skill_sdk/plugins/file_watcher.py
agent_skill_sdk/plugins/http.py
agent_skill_sdk/plugins/mqtt.py
agent_skill_sdk/plugins/timer.py
agent_skill_sdk/reasoning/bedrock.py
agent_skill_sdk/reasoning/templates.py
agent_skill_sdk/skills/__init__.py
agent_skill_sdk/skills/basic.py
agent_skill_sdk-0.1.1.dist-info/licenses/LICENSE
agent_skill_sdk-0.1.1.dist-info/METADATA
agent_skill_sdk-0.1.1.dist-info/WHEEL
agent_skill_sdk-0.1.1.dist-info/entry_points.txt
agent_skill_sdk-0.1.1.dist-info/top_level.txt
agent_skill_sdk-0.1.1.dist-info/RECORD
