Metadata-Version: 2.4
Name: agent-skill-sdk
Version: 0.1.1
Summary: Modular, event-driven AI agent SDK with trigger plugins, LLM reasoning (Amazon Bedrock), retries, and a dashboard.
Author-email: Your Name <you@example.com>
License-Expression: MIT
Requires-Python: >=3.8
License-File: LICENSE
Requires-Dist: boto3
Requires-Dist: paho-mqtt
Requires-Dist: schedule
Requires-Dist: uvicorn
Requires-Dist: fastapi
Requires-Dist: watchdog
Requires-Dist: python-dotenv
Dynamic: license-file
